pppd.py
python_pppd-1.0.8.dist-info/LICENSE
python_pppd-1.0.8.dist-info/METADATA
python_pppd-1.0.8.dist-info/WHEEL
python_pppd-1.0.8.dist-info/top_level.txt
python_pppd-1.0.8.dist-info/RECORD
